aeonlib/__init__.py
aeonlib/conf.py
aeonlib/exceptions.py
aeonlib/models.py
aeonlib/py.typed
aeonlib/types.py
aeonlib/eso/__init__.py
aeonlib/eso/facility.py
aeonlib/eso/models.py
aeonlib/lt/__init__.py
aeonlib/lt/facility.py
aeonlib/lt/models.py
aeonlib/ocs/__init__.py
aeonlib/ocs/config_models.py
aeonlib/ocs/facility.py
aeonlib/ocs/request_models.py
aeonlib/ocs/target_models.py
aeonlib/ocs/blanco/__init__.py
aeonlib/ocs/blanco/facility.py
aeonlib/ocs/blanco/instruments.py
aeonlib/ocs/lco/__init__.py
aeonlib/ocs/lco/facility.py
aeonlib/ocs/lco/instruments.py
aeonlib/ocs/saao/__init__.py
aeonlib/ocs/saao/facility.py
aeonlib/ocs/saao/instruments.py
aeonlib/ocs/soar/__init__.py
aeonlib/ocs/soar/facility.py
aeonlib/ocs/soar/instruments.py
aeonlib-0.1.1.dist-info/METADATA
aeonlib-0.1.1.dist-info/WHEEL
aeonlib-0.1.1.dist-info/licenses/LICENSE
aeonlib-0.1.1.dist-info/RECORD
