Metadata-Version: 2.4
Name: aeonlib
Version: 0.1.1
Summary: A suite of modules to enable TDA/MMA observations
Author-email: Austin Riba <ariba@lco.global>
License-File: LICENSE
Requires-Python: >=3.12
Requires-Dist: astropy>=7.0.1
Requires-Dist: httpx>=0.28.1
Requires-Dist: pydantic-settings>=2.9.1
Requires-Dist: pydantic>=2.11.1
Provides-Extra: eso
Requires-Dist: p2api>=1.0.10; extra == 'eso'
Provides-Extra: lt
Requires-Dist: lxml-stubs>=0.5.1; extra == 'lt'
Requires-Dist: lxml>=5.4.0; extra == 'lt'
Requires-Dist: suds>=1.2.0; extra == 'lt'
